{
  "models": {
    "lstm_eurgbp": {
      "model_name": "LSTM_EUR/GBP",
      "model_type": "lstm",
      "currency_pair": "EUR/GBP",
      "model_id": "lstm_eurgbp",
      "created": "2025-09-01T19:40:13.442735",
      "file_path": "models/lstm_eurgbp/model.pth",
      "directory": "models/lstm_eurgbp",
      "model_info": {
        "model_type": "LSTMModel",
        "model_version": "1.0",
        "is_trained": true,
        "config": {
          "input_size": 80,
          "hidden_size": 128,
          "num_layers": 2,
          "dropout": 0.2,
          "bidirectional": false,
          "batch_size": 32,
          "learning_rate": 0.001,
          "epochs": 100,
          "patience": 15,
          "sequence_length": 30,
          "prediction_horizons": [
            1,
            7,
            30
          ],
          "train_test_split": 0.7,
          "validation_split": 0.15,
          "device": "cuda"
        },
        "parameter_count": 254278,
        "trainable_parameters": 254278,
        "architecture": {
          "input_size": 80,
          "hidden_size": 128,
          "num_layers": 2,
          "dropout": 0.2,
          "bidirectional": false,
          "output_size": 3
        },
        "prediction_horizons": [
          1,
          7,
          30
        ],
        "device": "cuda",
        "training_history_length": 35
      },
      "training_samples": 85,
      "features_count": 80,
      "performance_metrics": {
        "mse": 0.0003060771559830755,
        "mae": 0.015196477994322777,
        "rmse": 0.017495060902525474,
        "r2": -2.5926887567720382,
        "directional_accuracy": 0.48433048433048437,
        "mean_uncertainty": 0.0005649197264574468,
        "directional_accuracy_1d": 0.45726495726495725,
        "directional_accuracy_7d": 0.4658119658119658,
        "directional_accuracy_30d": 0.5299145299145299
      },
      "training_history": {
        "loss": [
          0.07590172191460927,
          0.07030308494965236,
          0.06288993979493777,
          0.05668447042504946,
          0.04733231539527575,
          0.03836896394689878,
          0.03002047787110011,
          0.02267737252016862,
          0.016473195515573025,
          0.011615839476386705,
          0.007880312701066336,
          0.0054341577924788,
          0.003937829130639632,
          0.0029774769209325314,
          0.002197970791409413,
          0.0018892552082737286,
          0.0013358952710404992,
          0.0011424891805897157,
          0.0010525496521343787,
          0.0008989142758461336,
          0.000858018989674747,
          0.0007532224214325348,
          0.0006430011708289385,
          0.000716939529714485,
          0.0007657292687023679,
          0.0006607466105682155,
          0.0005242873060827454,
          0.0005014509273072084,
          0.0004686801403295249,
          0.00048663487541489303,
          0.0004471972254881014,
          0.00047843754873611033,
          0.00042666417236129445,
          0.00044790095610854525,
          0.0004205994482617825
        ],
        "val_loss": [
          0.0057776146568357944,
          0.0011316442396491766,
          0.001971190795302391,
          0.00023969978792592883,
          0.0004023882793262601,
          0.00029175341478548944,
          0.0002764104283414781,
          0.00037395229446701705,
          0.00020468533330131322,
          0.0001605666766408831,
          0.0002377342461841181,
          0.00015741439710836858,
          0.0002751910360530019,
          0.00011335252202115953,
          0.00015395005175378174,
          0.00016245072765741497,
          0.00010590436431812122,
          0.00019275066733825952,
          0.00013251199561636895,
          0.00010503024532226846,
          0.00022616094793193042,
          0.00014469113375525922,
          0.00013346319610718638,
          0.0001224996376549825,
          0.0001320710580330342,
          0.0001359391026198864,
          0.0001552676985738799,
          0.00011093055945821106,
          0.00017657046555541456,
          0.0001111721430788748,
          0.00017457795911468565,
          0.0001845407095970586,
          0.00012052656529704109,
          0.00015038522542454302,
          0.0002759556518867612
        ]
      },
      "data_days": 365
    },
    "lstm_eurcad": {
      "model_name": "LSTM_EUR/CAD",
      "model_type": "lstm",
      "currency_pair": "EUR/CAD",
      "model_id": "lstm_eurcad",
      "created": "2025-09-01T20:13:08.251410",
      "file_path": "models/lstm_eurcad/model.pth",
      "directory": "models/lstm_eurcad",
      "model_info": {
        "model_type": "LSTMModel",
        "model_version": "1.0",
        "is_trained": true,
        "config": {
          "input_size": 80,
          "hidden_size": 128,
          "num_layers": 2,
          "dropout": 0.2,
          "bidirectional": false,
          "batch_size": 32,
          "learning_rate": 0.001,
          "epochs": 100,
          "patience": 15,
          "sequence_length": 30,
          "prediction_horizons": [
            1,
            7,
            30
          ],
          "train_test_split": 0.7,
          "validation_split": 0.15,
          "device": "cuda"
        },
        "parameter_count": 254278,
        "trainable_parameters": 254278,
        "architecture": {
          "input_size": 80,
          "hidden_size": 128,
          "num_layers": 2,
          "dropout": 0.2,
          "bidirectional": false,
          "output_size": 3
        },
        "prediction_horizons": [
          1,
          7,
          30
        ],
        "device": "cuda",
        "training_history_length": 30
      },
      "training_samples": 501,
      "features_count": 80,
      "performance_metrics": {
        "mse": 9.782401320990175e-05,
        "mae": 0.00783221609890461,
        "rmse": 0.009890602267299082,
        "r2": -0.0039801383039190785,
        "directional_accuracy": 0.5158327290306985,
        "mean_uncertainty": 0.0001365357165923342,
        "directional_accuracy_1d": 0.5192168237853517,
        "directional_accuracy_7d": 0.5170413343002176,
        "directional_accuracy_30d": 0.5112400290065264
      },
      "training_history": {
        "loss": [
          0.05460156931076199,
          0.010930232849204913,
          0.0020761715350090526,
          0.0010021785201388411,
          0.0007314634676731657,
          0.0006208380364114419,
          0.0005378466084948741,
          0.00044694754797092173,
          0.00038786678305768874,
          0.00036401443867362104,
          0.0003285150269221049,
          0.00031039759414852597,
          0.0002805652275128523,
          0.00025561142138030846,
          0.00024747939369262895,
          0.000214598502680019,
          0.00022592063851334387,
          0.00020294899059081217,
          0.00019650592730613425,
          0.00018584066856419668,
          0.00017865105837699957,
          0.00017210230635100743,
          0.00016510292516613845,
          0.00015719830662419554,
          0.00015870373954385286,
          0.0001577366397214064,
          0.0001570985550642945,
          0.00015029586120363092,
          0.0001489971145929303,
          0.00013701558327738894
        ],
        "val_loss": [
          0.0002954808296635747,
          0.0001269790082005784,
          0.00010456824384164065,
          0.00016754482930991799,
          0.00020482797117438167,
          0.00011929766333196312,
          0.0001486449909862131,
          0.00010864862997550517,
          0.00011363060912117362,
          0.00011641135643003508,
          0.00010310688958270475,
          0.0001053156447596848,
          0.0001047674086294137,
          0.0001039502167259343,
          0.00010199169628322124,
          0.00010262292926199734,
          0.00010349205695092678,
          0.00010856330482056364,
          0.00010218566603725776,
          0.00010334631951991469,
          0.00010359023872297257,
          0.00010205715807387605,
          0.00010202049452345818,
          0.00010282789298798889,
          0.0001023419972625561,
          0.00010297069820808247,
          0.00010236544767394662,
          0.00010232956992695108,
          0.00010397654114058241,
          0.00010211134940618649
        ]
      },
      "data_days": 2000
    },
    "lstm_usdeur": {
      "model_name": "LSTM_USD/EUR",
      "model_type": "lstm",
      "currency_pair": "USD/EUR",
      "model_id": "lstm_usdeur",
      "created": "2025-09-01T21:40:43.246515",
      "file_path": "/home/spandan/projects/spec_project_2/currency_assistant/models/lstm_usdeur/model.pth",
      "directory": "/home/spandan/projects/spec_project_2/currency_assistant/models/lstm_usdeur",
      "model_info": {
        "model_type": "LSTMModel",
        "model_version": "1.0",
        "is_trained": true,
        "config": {
          "input_size": 81,
          "hidden_size": 128,
          "num_layers": 2,
          "dropout": 0.2,
          "bidirectional": false,
          "batch_size": 32,
          "learning_rate": 0.001,
          "epochs": 100,
          "patience": 15,
          "sequence_length": 30,
          "prediction_horizons": [
            1,
            7,
            30
          ],
          "train_test_split": 0.7,
          "validation_split": 0.15,
          "device": "cuda"
        },
        "parameter_count": 254790,
        "trainable_parameters": 254790,
        "architecture": {
          "input_size": 81,
          "hidden_size": 128,
          "num_layers": 2,
          "dropout": 0.2,
          "bidirectional": false,
          "output_size": 3
        },
        "prediction_horizons": [
          1,
          7,
          30
        ],
        "device": "cuda",
        "training_history_length": 37
      },
      "training_samples": 501,
      "features_count": 81,
      "performance_metrics": {
        "mse": 9.801558189792559e-05,
        "mae": 0.007843967527151108,
        "rmse": 0.009900281910022844,
        "r2": -0.005946191309003757,
        "directional_accuracy": 0.5158327290306985,
        "mean_uncertainty": 0.0001353308034595102,
        "directional_accuracy_1d": 0.5192168237853517,
        "directional_accuracy_7d": 0.5170413343002176,
        "directional_accuracy_30d": 0.5112400290065264
      },
      "training_history": {
        "loss": [
          0.06505528558045626,
          0.019979183445684612,
          0.004681636957684532,
          0.002037537589785643,
          0.0013333466267795302,
          0.0011101592717750464,
          0.0008936677149904426,
          0.0008293627797684167,
          0.0007121408634702675,
          0.0005482190044858726,
          0.0005588224958046339,
          0.0005049147894169437,
          0.0005036748989368789,
          0.00043214927063672803,
          0.0003966959011449944,
          0.00037337091271183454,
          0.00032689965883037075,
          0.0003092516326432815,
          0.0002933321311502368,
          0.0002983316280733561,
          0.0002654835761859431,
          0.0002646992734298692,
          0.0002508998732082546,
          0.00023847092779760715,
          0.00022401346450351411,
          0.00022077457651903387,
          0.0002162949531339109,
          0.00020246476469765184,
          0.00020210607090120902,
          0.00019587475981097668,
          0.00018922598883364117,
          0.00017699463751341682,
          0.0001841732073444291,
          0.00017454113185522147,
          0.00016705392499716254,
          0.0001681922331044916,
          0.00016300634570143302
        ],
        "val_loss": [
          0.0020402083173394203,
          0.00018771679606288671,
          0.0002866229915525764,
          0.0003548643144313246,
          0.00011341679783072323,
          0.00019106475519947708,
          0.00013587622379418463,
          0.00012786062143277377,
          0.00016657596279401332,
          0.0001722621382214129,
          0.00010395720164524391,
          0.00014002210809849203,
          0.00014150601055007428,
          0.0001033219086821191,
          0.00011831654410343617,
          0.00010575215128483251,
          0.00010855247819563374,
          0.00010784083133330569,
          0.00011689570965245366,
          0.00012776405492331833,
          0.00010203577403444797,
          0.00010179466335102916,
          0.0001043340380419977,
          0.00011086813901783898,
          0.00010822680633282289,
          0.00010591260070214048,
          0.00011179196008015424,
          0.0001029396808007732,
          0.00010680595005396754,
          0.00010519957140786573,
          0.0001054726672009565,
          0.00010466764069860801,
          0.0001030341227306053,
          0.00010926086542895064,
          0.00010418846068205312,
          0.00010277824912918732,
          0.00010266929166391492
        ]
      },
      "data_days": 2000
    },
    "lstm_usdeur_20250901_221946": {
      "model_name": "LSTM_USD/EUR_20250901_221946",
      "model_type": "lstm",
      "currency_pair": "USD/EUR",
      "model_id": "lstm_usdeur_20250901_221946",
      "created": "2025-09-01T22:19:46.493765",
      "file_path": "models/lstm_usdeur_20250901_221946/model.pth",
      "directory": "models/lstm_usdeur_20250901_221946",
      "model_info": {
        "model_type": "LSTMModel",
        "model_version": "1.0",
        "is_trained": true,
        "config": {
          "input_size": 81,
          "hidden_size": 128,
          "num_layers": 2,
          "dropout": 0.2,
          "bidirectional": false,
          "batch_size": 32,
          "learning_rate": 0.001,
          "epochs": 100,
          "patience": 15,
          "sequence_length": 60,
          "prediction_horizons": [
            1,
            7,
            30
          ],
          "train_test_split": 0.8,
          "validation_split": 0.2,
          "device": "cuda"
        },
        "parameter_count": 254790,
        "trainable_parameters": 254790,
        "architecture": {
          "input_size": 81,
          "hidden_size": 128,
          "num_layers": 2,
          "dropout": 0.2,
          "bidirectional": false,
          "output_size": 3
        },
        "prediction_horizons": [
          1,
          7,
          30
        ],
        "device": "cuda",
        "training_history_length": 61
      },
      "training_samples": 21,
      "features_count": 81,
      "performance_metrics": {
        "mse": 0.0001701814035186544,
        "mae": 0.010946924798190594,
        "rmse": 0.013045359462991214,
        "r2": -1.2094235548785517,
        "directional_accuracy": 0.5416666666666666,
        "mean_uncertainty": 0.002308478346094489,
        "directional_accuracy_1d": 0.5357142857142857,
        "directional_accuracy_7d": 0.5089285714285714,
        "directional_accuracy_30d": 0.5803571428571429
      },
      "training_history": {
        "loss": [
          0.08232451230287552,
          0.07779417186975479,
          0.072911337018013,
          0.0674588605761528,
          0.06350550055503845,
          0.06066051125526428,
          0.05838155746459961,
          0.05455967038869858,
          0.05184182524681091,
          0.049046192318201065,
          0.04510072246193886,
          0.041465964168310165,
          0.03777275234460831,
          0.03436044231057167,
          0.03067425638437271,
          0.02837451361119747,
          0.025480909273028374,
          0.023377027362585068,
          0.019919518381357193,
          0.017861153930425644,
          0.015566972084343433,
          0.013405825011432171,
          0.012239670380949974,
          0.010221479460597038,
          0.00908750668168068,
          0.007873021066188812,
          0.007031396962702274,
          0.006343953311443329,
          0.006033831741660833,
          0.005070988088846207,
          0.004606116563081741,
          0.00443408265709877,
          0.0032268413342535496,
          0.003084861673414707,
          0.0034457312431186438,
          0.0029674863908439875,
          0.0021470484789460897,
          0.0026937176007777452,
          0.002143485937267542,
          0.001826740219257772,
          0.0024565488565713167,
          0.002784497570246458,
          0.002090721856802702,
          0.001954374834895134,
          0.002163603203371167,
          0.0022542448714375496,
          0.002032306045293808,
          0.0022424550261348486,
          0.0011686710640788078,
          0.0015922458842396736,
          0.0023719044402241707,
          0.0018997229635715485,
          0.001545382896438241,
          0.0013029722031205893,
          0.0018265029648318887,
          0.0017914300551638007,
          0.0013868216192349792,
          0.001243945094756782,
          0.002049804897978902,
          0.0012479701545089483,
          0.0015242077643051744
        ],
        "val_loss": [
          0.01241468545049429,
          0.009012800641357899,
          0.0057145943865180016,
          0.002632729010656476,
          0.0009727130527608097,
          0.0017946040024980903,
          0.0019444756908342242,
          0.0011135441018268466,
          0.00039132245001383126,
          0.0004886321257799864,
          0.0009518180740997195,
          0.0008291624835692346,
          0.0004511692968662828,
          0.0003211934817954898,
          0.00036901491694152355,
          0.0004270832287147641,
          0.00041486829286441207,
          0.0003633132728282362,
          0.0004459761257749051,
          0.0006235803593881428,
          0.0006388499750755727,
          0.0005799860809929669,
          0.00045887933811172843,
          0.0003542960621416569,
          0.0003207077388651669,
          0.0002761653158813715,
          0.000223652517888695,
          0.00016138503269758075,
          0.00029711041133850813,
          0.00048283953219652176,
          0.00045059260446578264,
          0.00039688273682259023,
          0.00038602182758040726,
          0.0003521415637806058,
          0.00022297787654679269,
          0.00013306165055837482,
          0.00016056816093623638,
          0.0002747153921518475,
          0.000498782901559025,
          0.0007027190295048058,
          0.0005600246367976069,
          0.00027363080880604684,
          0.00012011629587505013,
          8.792637527221814e-05,
          8.260380855062976e-05,
          6.423296144930646e-05,
          0.0001930829166667536,
          0.00048615297419019043,
          0.0009150787373073399,
          0.0010972919408231974,
          0.0008030936005525291,
          0.0003828215994872153,
          0.00011223672481719404,
          9.670080180512741e-05,
          9.924434561980888e-05,
          0.00016520563804078847,
          0.00036543066380545497,
          0.0005145633476786315,
          0.00040629965951666236,
          0.00029655403341166675,
          0.00018303794786334038
        ]
      },
      "data_days": 200
    },
    "lstm_usdeur_20250901_222609": {
      "model_name": "LSTM_USD/EUR_20250901_222609",
      "model_type": "lstm",
      "currency_pair": "USD/EUR",
      "model_id": "lstm_usdeur_20250901_222609",
      "created": "2025-09-01T22:26:09.296511",
      "file_path": "models/lstm_usdeur_20250901_222609/model.pth",
      "directory": "models/lstm_usdeur_20250901_222609",
      "model_info": {
        "model_type": "LSTMModel",
        "model_version": "1.0",
        "is_trained": true,
        "config": {
          "input_size": 64,
          "hidden_size": 128,
          "num_layers": 2,
          "dropout": 0.2,
          "bidirectional": false,
          "batch_size": 32,
          "learning_rate": 0.001,
          "epochs": 100,
          "patience": 15,
          "sequence_length": 60,
          "prediction_horizons": [
            1,
            7,
            30
          ],
          "train_test_split": 0.8,
          "validation_split": 0.2,
          "device": "cuda"
        },
        "parameter_count": 246086,
        "trainable_parameters": 246086,
        "architecture": {
          "input_size": 64,
          "hidden_size": 128,
          "num_layers": 2,
          "dropout": 0.2,
          "bidirectional": false,
          "output_size": 3
        },
        "prediction_horizons": [
          1,
          7,
          30
        ],
        "device": "cuda",
        "training_history_length": 20
      },
      "training_samples": 29,
      "features_count": 64,
      "performance_metrics": {
        "mse": 8.785051613813266e-05,
        "mae": 0.007719758898019791,
        "rmse": 0.009372860616595802,
        "r2": -1.9779974358957286,
        "directional_accuracy": 0.4746136865342164,
        "mean_uncertainty": 0.20582932233810425,
        "directional_accuracy_1d": 0.4966887417218543,
        "directional_accuracy_7d": 0.5298013245033113,
        "directional_accuracy_30d": 0.3973509933774834
      },
      "training_history": {
        "loss": [
          0.07282205671072006,
          0.07062902301549911,
          0.06946034729480743,
          0.0682724118232727,
          0.06715092062950134,
          0.06596335768699646,
          0.06412990391254425,
          0.0619877465069294,
          0.059111371636390686,
          0.055885735899209976,
          0.052290692925453186,
          0.048853565007448196,
          0.045305658131837845,
          0.04213395342230797,
          0.0387711264193058,
          0.0355638824403286,
          0.03234201297163963,
          0.029218656942248344,
          0.026104984804987907,
          0.023636985570192337
        ],
        "val_loss": [
          0.001703633926808834,
          0.001008500810712576,
          0.0005308440886437893,
          0.00024064024910330772,
          5.4388248827308416e-05,
          7.553796604042873e-05,
          0.00028085900703445077,
          0.00033814815105870366,
          0.00024379264505114406,
          0.00014181737788021564,
          0.0001477728656027466,
          0.00019388424698263407,
          0.0002006477297982201,
          0.00015512351819779724,
          0.00013696889800485224,
          0.00012949196388944983,
          0.00010822177864611149,
          0.00011441936658229679,
          0.00010330994700780138,
          9.11595270736143e-05
        ]
      },
      "data_days": 200
    }
  },
  "default_models": {
    "EUR/GBP": {
      "lstm": "lstm_eurgbp"
    },
    "EUR/CAD": {
      "lstm": "lstm_eurcad"
    },
    "USD/EUR": {
      "lstm": "lstm_usdeur_20250901_222609"
    }
  },
  "created": "2025-09-01T19:40:10.519696",
  "last_updated": "2025-09-01T22:26:09.296957"
}